.gitignore
levdist/__init__.py
levdist/_classic.py
levdist/_native.cpp
levdist/_native.cpython-312-i386-linux-musl.so
levdist/_native.pyi
levdist/_wagner_fischer.py
levdist/py.typed
levdist.libs/libgcc_s-887de51c.so.1
levdist.libs/libstdc++-d6415257.so.6.0.33
levdist-1.0.3.dist-info/METADATA
levdist-1.0.3.dist-info/WHEEL
levdist-1.0.3.dist-info/entry_points.txt
levdist-1.0.3.dist-info/RECORD
levdist-1.0.3.dist-info/licenses/LICENSE
