Metadata-Version: 2.1
Name: levdist
Version: 1.0.3
Summary: Package to calculate the Levenstein distance
Keywords: levenstein,edit distance
Author-Email: Dmitry Erlikh <derlih@gmail.com>
License: MIT
Classifier: Development Status :: 5 - Production/Stable
Classifier: License :: OSI Approved :: MIT License
Classifier: Typing :: Typed
Classifier: Programming Language :: Python :: Implementation :: CPython
Classifier: Programming Language :: Python :: Implementation :: PyPy
Classifier: Programming Language :: Python :: 3.9
Classifier: Programming Language :: Python :: 3.10
Classifier: Programming Language :: Python :: 3.11
Classifier: Programming Language :: Python :: 3.12
Classifier: Programming Language :: Python :: 3.13
Project-URL: Homepage, https://github.com/derlih/levdist
Project-URL: Issues, https://github.com/derlih/levdist/issues
Requires-Python: >=3.9
